{
  "a_id": "ERNdEqzXgCLtmun0JWbfSSU0kZ0=",
  "a_publication": "insm_presse",
  "a_date": "2014-05-20T00:00:00",
  "a_author": null,
  "a_url": "https://www.insm.de/insm/presse/pressemeldungen/marktwirtschaftlicher-dialog-zum-rentenpaket",
  "a_text": "Marktwirtschaftlicher Dialog zum Rentenpaket\nDas Rentenpaket bleibt ein politischer Zankapfel. Beim „Marktwirtschaftlichen Dialog“ der Initiative Neue Soziale Marktwirtschaft (INSM) heute in Berlin, stritten sich Union, SPD und Grüne über die Folgen der aktuellen Regierungspolitik. 20. Mai 2014 Markus Kurth, MdB, rentenpolitischer Sprecher von Bündnis 90/Die Grünen: „Zwar erheben Union und SPD mit dem Rentenpaket den Anspruch, Gerechtigkeitslücken zu schließen und Lebensleistung besser anzuerkennen. Die Umsetzung dieses Anliegens geht jedoch auf Kosten der Personengruppen, die es eigentlich am nötigsten haben. Das Vorhaben geht an den sozialpolitisch vordringlichen Aufgaben vorbei.\" Auch für Dr. Carsten Linnemann, MdB, Vorsitzender der Mittelstands- und Wirtschaftsvereinigung (MIT) der CDU/CSU, hat das Rentenpaket einen Makel: „Die Rente mit 63 hat einen schweren Geburtsfehler, denn Zeiten von Arbeitslosigkeit werden genauso behandelt wie Zeiten von Arbeit. Deshalb müssen wir so schnell wie möglich zurück zur alten Regel, wonach nur Zeiten von Arbeit gelten.“ Dr. Martin Rosemann, MdB, federführender Berichterstatter der SPD-Fraktion für die Rentenpolitik, verteidigte das Rentenpaket: „Das Rentenpaket ist richtig, weil es Gerechtigkeitslücken schließt, die Lebensleistungen besser anerkennt und Erwerbsminderungsrentner besser stellt. Das ändert nichts daran, dass das reguläre gesetzliche Renteneintrittsalter wie geplant schrittweise erhöht wird. Generell gilt für mich: Prävention vor Reha vor Rente.“ Um der Rückkehr zur Frühverrentung entgegenzuwirken, hofft Linnemann auf die sogenannte Flexi-Rente „Wir brauchen ein Signal für diejenigen, die freiwillig länger arbeiten wollen. Ihnen dürfen keine Steine mehr in den Weg gelegt werden. Die Flexi-Rente ist ein erster Schritt in diese Richtung.“ Den Erfolg einer solchen Flexi-Rente sieht Prof. Dr. Reinhold Schnabel, Universität Duisburg-Essen, aber durch das Rentenpaket gefährdet: „Die Rente mit 63 hat für einen typischen Rentner mit 45 Beitragsjahren einen Wert von rund 30.000 Euro! Dieses Angebot wird kaum jemand ablehnen. Das Potential für ein Arbeiten im Rentenalter wird durch das Rentenpaket drastisch reduziert, weil mindestens 100.000 Fachkräfte im Alter von 64 und 65 Jahren aus dem Arbeitsmarkt genommen werden. Diese dürfen maximal einen Minijob machen. Und es wäre sozial- und wirtschaftspolitisch widersinnig, diesen Leuten auch noch eine anrechnungsfreie Beschäftigung zu erlauben, nachdem man sie subventioniert in Rente gehen lässt.“ Nach Meinung von Hubertus Pellengahr, Geschäftsführer der INSM, droht die Rentner-Demokratie, vor der Alt-Bundespräsident Roman Herzog 2008 warnte: „Roman Herzog konnte vor sechs Jahren von dem diese Woche zur Abstimmung stehenden Rentenpaket noch nichts ahnen. Seine damalige Sorge, dass die Älteren die Jüngeren ausplündern, erscheint angesichts der aktuellen Regierungspolitik leider berechtigt.“ Pressekontakt Pressesprecher INSM: Florian von Hennet, Tel. 030 27877-174; hennet@insm.de",
  "b_id": "fVFT8LZfQ/W/dbpFg66xcUkVGqc=",
  "b_publication": "RND_de",
  "b_date": "2021-03-09T00:00:00",
  "b_author": "Tobias Peter",
  "b_url": "https://www.rnd.de/politik/maskenaffare-in-union-spd-will-bestechung-mit-zehn-punkte-plan-bekampfen-U3XWINHHFJCV7E647C33BJ4WUQ.html",
  "b_text": "Härtere Regeln nach Maskenaffäre: SPD will Bestechung mit Zehn-Punkte-Plan bekämpfen\nStartseite Politik Maskenaffäre in Union: SPD will Bestechung mit Zehn-Punkte-Plan bekämpfen Härtere Regeln nach Maskenaffäre: SPD will Bestechung mit Zehn-Punkte-Plan bekämpfen Die Maskenaffäre in der Union erschüttert das politische Berlin. Die SPD legt jetzt einen Plan vor, wie die Gesetze gegen Abgeordnetenbestechung verschärft werden sollen – und wie darüber hinaus die Transparenz über Abgeordneteneinkünfte erhöht werden kann. SPD-Fraktionschef Rolf Mützenich fordert die CDU zu Gesprächen noch in dieser Woche auf. Berlin. Die SPD fordert die Union auf, aus der Maskenaffäre Konsequenzen zu ziehen und in der großen Koalition gemeinsam verschärfte Gesetze im Kampf gegen Abgeordnetenbestechung und zur Transparenz bei Nebeneinkünften zu beschließen. „Die Maskenaffäre bei der Union muss rechtliche Konsequenzen haben, so wie wir sie seit Langem schon von unserem Koalitionspartner fordern“, sagte SPD-Fraktionschef Rolf Mützenich dem RedaktionsNetzwerk Deutschland (RND). „Es geht eben nicht nur um Aufarbeitung der Einzelfälle und auch nicht um interne Complianceregeln im Sinne einer Art Selbstverpflichtung, wie sie die Union plant“, setzte Mützenich hinzu. Die SPD wolle darüber mit der Union noch in dieser Woche sprechen, sagte der SPD-Fraktionschef. „Das wird dann die erste Bewährungsprobe, ob CDU und CSU endlich bereit sind, sich in diesen Bereichen nach jahrelanger Blockade zu bewegen.“ Schärfere Regeln in drei Bereichen Notwendig seien klare und verschärfte gesetzliche Regeln in drei Bereichen, forderte Mützenich: „Wir müssen die Sanktionen beim Lobbyregister verschärfen und den sogenannten exekutiven Fußabdruck einführen“, sagte er. „Wir müssen die Anzeigepflichten bei Nebentätigkeiten und Nebeneinkünften im Abgeordnetengesetz ausweiten, um für mehr Transparenz zu sorgen“, fuhr er fort. „Und wir müssen Strafen für Bestechung und Bestechlichkeit im Parlament verschärfen, um deutlich zu machen, dass es sich hier nicht um Kavaliersdelikte dreht, sondern um schwere Kriminalität.“ Mützenich betonte: „An diese Regeln müssen sich dann alle halten, ansonsten müssen Regelbrecher spürbar sanktioniert werden.“ In einem Zehn-Punkte-Plan der SPD-Fraktion, der dem RND vorliegt, verlangt die SPD sowohl Änderungen des Strafgesetzbuches als auch des Abgeordnetengesetzes. So sollen Abgeordnetenbestechung und -bestechlichkeit in Paragraf 108e des Strafgesetzbuches künftig nicht mehr als Vergehen, sondern als Verbrechen eingestuft werden. Die Mindeststrafe soll nach SPD-Vorstellungen auf ein Jahr Freiheitsstrafe erhöht werden. Abgeordnete müssten künftig, so fordert es die SPD, auch den Umfang ihrer Nebentätigkeiten angeben, also wie viele Stunden diese Nebentätigkeiten im Monat oder im Jahr in Anspruch nehmen. Auf diese Weise werde offengelegt, ob das Mandat immer noch im Mittelpunkt der Arbeit der jeweiligen Abgeordneten stehe. Weitere Punkte auf der Forderungsliste der SPD: Aktienoptionen sollen künftig anzeige- und veröffentlichungspflichtig werden – und das unabhängig von der Frage, ob sie einen bezifferbaren Wert haben. Abgeordnete müssten zudem Unternehmensbeteiligungen bei Kapital- und Personengesellschaften künftig bereits ab 5 Prozent der Stimmrechte anzeigen – statt wie bislang erst ab 25 Prozent Unternehmensbeteiligung. Die Frage nach den Parteispenden Entgeltliche Lobbytätigkeiten neben dem Mandat wie beispielsweise die Politikberatung in Lobbyagenturen oder Unternehmen gehörten verboten, fordert die SPD. Für Mandatsträger solle ein Annahmeverbot für Spenden gelten. Nebeneinkünfte von Abgeordneten müssten auf Euro und Cent genau veröffentlicht werden. Für Parteispenden solle künftig eine jährliche Höchstgrenze von 100.000 Euro pro Spender gelten, so der Plan aus der SPD-Fraktion. Die Veröffentlichungspflicht von Parteispenden müsse darüber hinaus von 10.000 Euro auf 2000 Euro gesenkt werden. Zudem solle Sponsoring im Parteiengesetz geregelt werden. Bei Gesetzgebungsvorhaben solle die Bundesregierung immer die Treffen von Lobbyisten in Bundesministerien und deren Stellungnahmen oder Forderungspapiere veröffentlichen, also den sogenannten exekutiven Fußabdruck sichtbar machen.",
  "scores": "{\"1\": 0.2462686567164179, \"2\": 0.04143126177024482, \"3\": 0.003316749585406302, \"4\": 0.0, \"5\": 0.0, \"hapax\": 0.08620689655172414, \"1_mod\": 0.8556044289397846, \"2_mod\": 0.13347022587268995, \"3_mod\": 1.0, \"4_mod\": 0.0, \"5_mod\": 0.0}"
}