{
  "a_id": "kpNELW/tFREvTmL6DezDLAmvMz4=",
  "a_publication": "insm_presse",
  "a_date": "2015-06-15T00:00:00",
  "a_author": null,
  "a_url": "https://www.insm.de/insm/presse/pressemeldungen/ttip-studie",
  "a_text": "Studie: TTIP wäre das richtige Signal\nDie Transatlantische Handels- und Investitionspartnerschaft (TTIP) könnte gegen ein wichtiges Liberalisierungssignal setzen, langfristig Arbeitsplätze sichern und zu mehr Wohlstand bei den Konsumenten und auf beiden Seiten des Atlantiks führen, so das Ergebnis eines Gutachten des Instituts der deutschen Wirtschaft Köln (IW). 15. Juni 2015 Pressemeldung TTIP-StudieINSM-Position zu TTIPPodcast zu InvestorenschutzWas TTIP bringt (Die Welt)Was TTIP bringt (Blog) Der freie Warenverkehr, dem der Exportweltmeister Deutschland seinen hohen Lebensstandard verdankt, ist in Gefahr. Protektionismus und Globalisierungsskepsis nehmen in der Welthandelspolitik zu. Die Transatlantische Handels- und Investitionspartnerschaft (TTIP) zwischen den USA und der EU könnte gegen diesen Trend ein wichtiges Liberalisierungssignal setzen, langfristig Arbeitsplätze sichern und zu mehr Wohlstand bei den Konsumenten und auf beiden Seiten des Atlantiks führen. Zu diesem Ergebnis kommt ein Gutachten des Instituts der deutschen Wirtschaft Köln (IW) im Auftrag der Initiative Neue Soziale Marktwirtschaft (INSM). Allein im Industriewarenhandel könnten nach IW-Schätzungen rund 3,5 Milliarden Euro Zollabgaben wegfallen, die bisher Güter unnötig verteuern. Besonders kleinen und mittleren Unternehmen würden durch die Partnerschaft neue Exportmöglichkeiten eröffnet. „Grenzüberschreitender Handel ist Teil des Deutschland-Prinzips und eine tragende Säule der Sozialen Marktwirtschaft. Ohne freien Zugang zum Weltmarkt hätte Deutschland weder den Wiederaufbau, noch die Wiedervereinigung meistern können. Wenn TTIP scheitert, geraten Arbeitsplätze in Gefahr, die Wirtschaftskraft sinkt und unsere ohnehin belasteten Sozialkassen geraten unter Druck“, kommentiert INSM-Geschäftsführer Hubertus Pellengahr die Ergebnisse der Studie. „Die meisten von den TTIP-Skeptikern hervorgebrachten Kritikpunkte erweisen sich bei genauer Betrachtung als überzogen und ideologisch motiviert. Die berechtigten Sorgen müssen hingegen adressiert und ernst genommen werden. Unlösbare Probleme sehe ich nicht“, so Studienautor Jürgen Matthes. So sollte beispielsweise die Verhandlungstransparenz so hoch sein, dass Parlamente und Öffentlichkeit ausreichend informiert sind und sie die Verhandlungen effizient und konstruktiv begleiten können. Genauso müsse überprüft werden, dass die Zusagen der Politik über die Beibehaltung der Verbraucher-, Umwelt- und Gesundheitsschutzstandards eingehalten werden und es zu keiner Absenkung der EU-Standards kommt. TTIP sollte als Chance zur Gestaltung begriffen werden. „Ein Scheitern der Verhandlungen würde ein fatales Signal über die Handlungsfähigkeit Deutschlands und Europas an die Welt senden. Wenn Europa nicht seine hohen Standards mit den USA gemeinsam festlegt, werden andere sich mit geringeren zufrieden geben“, so die Befürchtung Pellengahrs. Pressesprecher Tel.: 030-27877 174 Fax.: 030-27877 181 E-Mail: hennet@insm.de Twitter: @INSMPresse",
  "b_id": "aj1sZo1uUI/bQoF4MjmsH6rnVuM=",
  "b_publication": "BILD",
  "b_date": "2021-05-14T00:00:00",
  "b_author": "Rüdiger Stumpf",
  "b_url": "https://www.bild.de/geld/wirtschaft/wirtschaft/krypto-kurssturz-nach-musk-tweet-was-wird-jetzt-aus-meinen-bitcoins-76379308.bild.html",
  "b_text": "Krypto-Kurssturz nach Tweet von Elon Musk: Was wird jetzt aus meinen Bitcoins?\nKrypto-Kurssturz nach Elon-Musk-Tweet | Was wird jetzt aus meinen Bitcoins? Mega-Kurssturz beim Bitcoin! In der Nacht zum Donnerstag sackte der Kurs der Kryptowährung überraschend um mehr als 15 Prozent in die Tiefe. Hintergrund: Einige Minuten zuvor hatte Tesla-Chef Elon Musk einen Tweet abgesetzt, in dem er verkündete, dass der US-amerikanische Elektro-Autobauer die Bezahlung mit der digitalen Währung Bitcoin für den Kauf seiner Fahrzeuge stoppt. Als Begründung nannte Musk den hohen Stromverbrauch für den Handel, aber vor allem für das Schürfen („Mining“) neuer Bitcoins. Offenbar hat der Tesla-Chef plötzlich Bedenken wegen des extremen Verbrauchs fossiler Brennstoffe. „Die Kryptowährung ist auf vielen Ebenen eine gute Idee und wir glauben an eine vielversprechende Zukunft, aber das kann nicht zu großen Lasten der Umwelt gehen.“, so Musk auf Twitter. Solange die Energie-Bilanz nicht besser werde, wolle Tesla keinen Bitcoin-Handel mehr betreiben. Folge: Der Bitcoin-Kurs sackte wenige Minuten später um gute 15 Prozent in den Keller. Selbst am frühen Nachmittag lag das Minus noch bei 11 Prozent im Vergleich zum Vortag. Der Bitcoin kostete gegen 15 Uhr knapp 42 000 Euro. Auch andere digitale Währungen, etwa Ethereum oder Lithereum hatten mit -12 Prozent und -16 Prozent fette Einbußen kassiert. Doch was bedeutet das nun für die Anleger? Auch Interessant Lesen Sie auch Kurssturz bei Kryptos Tesla stoppt Bitcoin-Zahlungen Die Umweltbilanz von Bitcoin gilt als problematisch. Und genau daran stört sich Tesla-Chef Elon Musk! Krypto-Gewitter! Der US-Elek... ANZEIGE: Günstige Kurse - Jetzt einsteigen! Bitcoin & Co. ganz einfach mit der Börse Stuttgart Digital Exchange handeln Anleger sollten ganz ruhig bleiben Die gute Nachricht: Es gibt keinen Grund zur Panik. „Alle Anleger, die in Bitcoin investiert haben, sollten in meinen Augen einfach Ruhe bewahren“ sagt Sven Hildebrandt, Chef der Hamburger Blockchain-Spezialberatung Distributed Ledger Consulting, zu BILD. Heißt: Sie sollten die Verluste aussitzen und nicht ohne Not verkaufen. Er setzt die aktuellen Schwankungen auf dem Krypto-Markt ins Verhältnis zum Kursanstieg der zurückliegenden zwölf Monate und beruhigt: „Wer vor einem Jahr eingestiegen ist, hat ein Plus von mehr als 450 Prozent erlebt. Bitcoin wurde schon 100 Mal totgesagt und ist zurecht noch immer quicklebendig“, so Hildebrandt zu BILD. Ob Bitcoin oder Ethereum – künftig würden Kryptowerte weiter an Bedeutung gewinnen, meint der Hamburger Experte Hildebrandt. Gleichzeitig macht er deutlich: Anlagen in digitales Krypto-Geld sind nichts für schwache Nerven. Sein Tipp: Anleger sollten nur einen kleinen Teil ihres Vermögens in Bitcoin oder Ethereum investieren – oder nur das Geld, das übrig ist.",
  "scores": "{\"1\": 0.20077220077220076, \"2\": 0.02708803611738149, \"3\": 0.00646551724137931, \"4\": 0.0, \"5\": 0.0, \"hapax\": 0.05851063829787234, \"1_mod\": 0.8074534161490683, \"2_mod\": 0.057971014492753624, \"3_mod\": 1.0, \"4_mod\": 0.0, \"5_mod\": 0.0}"
}