{
  "a_id": "hcT36bEsA/bMPW8pRpx+sFWnBhY=",
  "a_publication": "insm_presse",
  "a_date": "2018-07-13T00:00:00",
  "a_author": null,
  "a_url": "https://www.insm.de/insm/presse/pressemeldungen/umfrage-zur-rente",
  "a_text": "Umfrage zur Rente\nDrei von vier Deutschen haben eine falsche Vorstellung von der Entwicklung der Renten. Das ist das Ergebnis einer repräsentativen Umfrage des Meinungsforschungsinstituts Civey im Auftrag der Initiative Neue Soziale Marktwirtschaft. Demnach glaubt die überwiegende Mehrheit der Deutschen nicht, dass die Kaufkraft der Renten auch in Zukunft steigen wird, sondern erwartet ein Absinken der Renten. Das ist aber das Gegenteil von dem, was Bundesregierung und Experten vorhersagen. 13. Juli 2018 Pressemeldung als PDFZur RentenkampagneINSM Position Rente Bundessozialminister Hubertus Heil hat sein Gesetzespaket für eine Rentenreform vorgelegt, das nach Überzeugung der Initiative Neue Soziale Marktwirtschaft die Politik der Großen Koalition auf Kosten der jungen und der zukünftigen Generation fortsetzt. Statt die Bevölkerung aufzuklären, spielt die Politik mit den Ängsten der Bürger. Die glauben nämlich mehrheitlich, dass die Renten in Zukunft sinken werden. Das aber wird nach der aktuellen Gesetzeslage nicht passieren. Im Gegenteil. Die INSM fordert deshalb von der Politik Aufklärung statt die Fortsetzung generationenungerechter rentenpolitischer Maßnahmen und startet mit der heutigen Vorstellung von Heils Rentenplänen ihre Kampagne „Geht’s noch, GroKo?”. Denn: Drei von vier Deutschen haben laut einer repräsentativen Umfrage des Meinungsforschungsinstituts Civey eine falsche Vorstellung von der Entwicklung der Renten. Demnach glaubt die Mehrheit der Deutschen nicht, dass die Kaufkraft der Renten auch in Zukunft steigen wird, sondern erwartet ein Absinken der Renten. Das ist jedoch das Gegenteil von dem, was die Bundesregierung prognostiziert: In dem 2017 von der damaligen Arbeits- und Sozialministerin Andrea Nahles (SPD) vorgelegten Rentenversicherungsbericht geht die Bundesregierung von einem Anstieg der Bruttostandardrente um über 30 Prozent bis zum Jahr 2031 aus. Prof. Dr. Axel Börsch-Supan (Mitglied der Rentenkommission) erwartet, dass nicht nur der Zahlbetrag, sondern auch die Kaufkraft der Renten in Zukunft weiter wachsen wird. Er geht von einem Kaufkraftanstieg um circa ein Prozent pro Jahr aus. Eine Rentnerin bzw. ein Rentner des Jahres 2035 könnte sich somit etwa 17 Prozent mehr leisten als eine vergleichbare Person heute. Der weitaus größte Teil der Bevölkerung weiß das entweder nicht oder glaubt den wissenschaftlichen Prognosen nicht. Lediglich zwei von einhundert Deutschen schätzt korrekt, dass die Kaufkraft der Renten bis 2035 um über zehn Prozent steigen wird, während 73 Prozent glauben, dass die Kaufkraft sinken wird. Rund 40 Prozent befürchten sogar einen Kaufkraftverlust von mehr als zehn Prozent. Dieser – nach wissenschaftlichem Stand der Forschung – falschen Vorstellung bei einem Großteil der Bevölkerung soll die Bundesregierung mit einer Aufklärungskampagne begegnen. Hubertus Pellengahr, Geschäftsführer der INSM: „Wenn sich herumspricht, dass sich die Rentner der nächsten Generation deutlich mehr leisten können, als heutige Rentner, könnte viel verlorenes Vertrauen in unser Rentensystem zurück gewonnen werden.” Die INSM fordert die Bundesregierung deshalb mit ihrer heute gestarteten Kampagne „Geht’s noch, GroKo?” auf, bei der gesetzlichen Rente wieder auf eine gerechte Verteilung der Lasten auf Alt und Jung zu achten. Unter anderem demonstrierte die INSM bereits heute Vormittag vor dem Bundesministerium für Arbeit und Soziales mit Kinderfahrrädern, auf deren Gepäckträgern überdimensionierte (Renten-)Pakete platziert waren. Pressesprecher Tel.: 030-27877 174 Fax.: 030-27877 181 E-Mail: hennet@insm.de Twitter: @INSMPresse",
  "b_id": "EYAOVNIl6j56+6tyzxCzhKqDcoE=",
  "b_publication": "faznet",
  "b_date": "2021-01-23T00:00:00",
  "b_author": "Annina Metz Und Manon Priebe",
  "b_url": "https://www.faz.net/aktuell/feuilleton/medien/rechtsstreit-bei-clubhouse-eva-hermann-erwirkt-widerruf-17161555.html",
  "b_text": "Rechtsstreit bei Clubhouse: Eva Herman erwirkt Widerruf von Richard Gutjahr\nDie Clubhouse-App ist noch neu in Deutschland, aber schon eine der beliebtesten Apps bei Apple Bild: Picture-Alliance Die frühere Nachrichtensprecherin Eva Herman hat einen Widerruf gegen den Journalisten Richard Gutjahr durchgesetzt. Anlass ist eine Diskussion über Fake-News in der Audio-App Clubhouse. 2 Min. Permalink: https://www.faz.net/-gsb-a7txv Mitten im Lockdown verlagert sich ein Teil der Empörungswellen langsam aber sicher auf das Portal Clubhouse. Dort können prominente und weniger prominente Persönlichkeiten Audio-Vorträge und Gesprächsrunden anberaumen. Wer Zugang zu den entsprechenden „Räumen“ bekommt, kann mitreden, sich also an den Diskussionen beteiligen. Anlass der letzten Aufwallung ist eine am 20. Januar organisierte Gesprächsrunde unter dem Titel „Lügenpresse? Was ist los im Journalismus“. An der Diskussion war eine Influencerin beteiligt, die rechtskonservative Positionen vertritt. Auch einige Journalisten debattierten mit. Im Anschluss daran diskutierten Nutzer der App und Twitternde darüber, ob derart radikale Meinungen auf dem Portal überhaupt so viel Raum bekommen sollten, ob man die Influencerin nicht wiederum zur anschließenden Diskussion zulassen hätte müssen – und ob Journalisten überhaupt öffentlich, also in der Wirklichkeit von Clubhouse, mit solchen Menschen reden sollten. Rechtspopulistische Theorien Als bei Twitter Screenshots von dem Gespräch veröffentlicht wurden, die Profilbilder von Teilnehmern und der Influencerin zeigten, schrieb der ebenfalls an der Gesprächsrunde beteiligte Journalist Richard Gutjahr auf Twitter: „Gegenfrage: Findest Du es okay, uns alle hier mit so einem Screenshot an den Pranger zu stellen? Die meisten Deiner Follower*innen müssen denken, wir hätten nicht kritisch mit ihr diskutiert. Gerade Du müsstest doch um der Wirkung eines solchen unfair verkürzten Tweets wissen.“ Kurz darauf folgte der nächste Konflikt. Gutjahr hatte bei der Veranstaltung gesagt: „Wenn von Euch mal einer hört, dass Eva Herman wieder in Deutschland ist, sagt mir Bescheid, ich habe noch einen Haftbefehl gegen sie.“ Die frühere NDR-Moderatorin und „Tagesschau“-Sprecherin ist in den vergangenen Jahren hauptsächlich mit rechtspopulistischen Aussagen und der Verbreitung von Verschwörungstheorien in Erscheinung getreten. Berichten zufolge soll sie in Kanada ein rechtes Netzwerk aufbauen und „Umsiedlungen“ dorthin organisieren, Herman dementiert das. „Mit Entsetzen erlebt“ Die Diskussionen werden auf Clubhouse mitgeschnitten. Wie der Branchendienst „Meedia“ berichtet, ging es Gutjahr eigentlich darum, dass Herman ihm noch Geld schulde und vor einer Zwangsvollstreckung nach Kanada ausgewandert sei. Einen „Haftbefehl“ gegen sie hatte er aber nicht. Hermans Anwalt Ralf Höcker, der überraschenderweise auch unter den Zuhörern der Clubhouse-Diskussion war, habe ihn darauf aufmerksam gemacht. Höcker wird mit den Worten zitiert: „Ich schätze Herrn Gutjahr sehr und habe die Hetzkampagne von Rechtsextremen, Antisemiten und Verschwörungstheoretikern gegen ihn mit Entsetzen erlebt. Auch deshalb sind wir nicht gleich mit einer kostenpflichtigen Abmahnung auf ihn losgegangen, sondern haben auf sein Verständnis gehofft. Mit Erfolg.“ Gutjahr wurde in den vergangenen Jahren immer wieder zur Zielscheibe von Verschwörungstheoretikern und Hetzkampagnen. Herman verzichtete laut „Meedia“ auf eine Abmahnung, Unterlassungserklärung und Erstattung der Anwaltskosten. Die Schulden, knapp 770 Euro, soll sie mittlerweile beglichen haben. Gutjahr wiederum veröffentliche seinen Widerruf auf Facebook. Ungezählte Debatten über rechtspopulistische Sprecher, über Repräsentation von Gruppen, Verantwortung, Verhältnismäßigkeit der digitalen Erregung und einer nötigen Regulierung durch die Betreiber hat die App Clubhouse in ihrer amerikanischen Ursprungsversion bereits hinter sich. Dort ist der große Hype um das Netzwerk inzwischen vorüber. Quelle: FAZ.NET Hier können Sie die Rechte an diesem Artikel erwerben.",
  "scores": "{\"1\": 0.18027210884353742, \"2\": 0.04020979020979021, \"3\": 0.0016233766233766235, \"4\": 0.0, \"5\": 0.0, \"hapax\": 0.052884615384615384, \"1_mod\": 0.8263633322181332, \"2_mod\": 0.057104913678618856, \"3_mod\": 1.0, \"4_mod\": 0.0, \"5_mod\": 0.0}"
}