{
  "a_id": "7rI4yYN0ahRU7JTS4x7IjnkgmCA=",
  "a_publication": "insm_presse",
  "a_date": "2007-05-13T00:00:00",
  "a_author": null,
  "a_url": "https://www.insm.de/insm/presse/pressemeldungen/kein-vertrauen-mehr-in-die-gesetzliche-pflegeversicherung",
  "a_text": "Drei von vier Bundesbürger würden lieber privat für das Pflegefallrisiko vorsorgen\nKein Vertrauen mehr in die gesetzliche Pflegeversicherung. Drei von vier berufstätigen Deutschen würden lieber zusätzliche Beiträge in eine private statt in eine gesetzliche Pflegeversicherung einzahlen. Das ergab eine Umfrage des Meinungsvorschungsinstituts forsa im Auftrag der Initiative Neue Soziale Marktwirtschaft. 13. Mai 2007 Demnach ziehen 77 Prozent der Bundesbürger eine eigene, kapitalgedeckte Vorsorge der gesetzlichen Pflichtversicherung vor. Vor dem Hintergrund der laufenden Beratungen in der großen Koalition in Berlin über die Pflegeversicherung sprechen die Bundesbürger der gesetzlichen Pflichtversicherung ein vernichtendes Urteil aus. Drei von vier berufstätigen Deutschen würden lieber zusätzliche Beiträge in eine private statt in die gesetzliche Pflegeversicherung einzahlen. Das ergab eine Umfrage des Meinungsforschungsinstituts forsa im Auftrag der Initiative Neue Soziale Marktwirtschaft. Demnach ziehen 77 Prozent der Bundesbürger eine eigene, kapitalgedeckte Vorsorge der gesetzlichen Pflichtversicherung vor. Nur 16 Prozent der Erwerbstätigen sprachen sich dafür aus, stattdessen höhere Beiträge in die umlagefinanzierte Pflegeversicherung einzuzahlen. Derzeit wird in der großen Koalition über eine Anhebung des gesetzlichen Beitrags zur Pflegeversicherung von 1,7 Prozent des Bruttolohns um 0,4 bis 0,6 Prozentpunkte und eine Leistungserweiterung für Demenzkranke diskutiert. Die klare Absage an die gesetzliche Pflegeversicherung wird dabei in Ostdeutschland (76 Prozent) und Westdeutschland (78) gleichermaßen geteilt. Allein Geringverdiener mit einem Haushaltsnettoeinkommen unter 1500 Euro sprachen sich etwas seltener (70 Prozent) für eine private Vorsorge aus. Zwei von drei Bundesbürgern wären dabei bereit, bis zu 20 Euro im Monat für die zusätzliche Absicherung im Alter auszugeben, um so der Gefahr vorzubeugen, im Alter zum Sozialfall zu werden. Dies ist ein Beitrag, der in etwa dem Modell der bayerischen Sozialministerin Christa Stewens (CSU) zur Reform der Pflegeversicherung entspricht. Der Stewens-Vorschlag sieht eine zusätzliche Prämie von 6 Euro im Monat vor, der nach und nach auf 20 Euro ansteigt. Gefragt wurden von forsa 1000 Bundesbürger im Alter von bis zu 50 Jahren. Die Pflegelücke, also die Differenz zwischen den notwendigen Ausgaben für die Pflege und den Leistungen der gesetzlichen Pflegeversicherung, beläuft sich bereits in diesem Jahr auf 8 Milliarden Euro. Im Jahr 2030 wird sie doppelt so hoch sein, wenn die Pflegeversicherung nicht rechtzeitig reformiert wird. Das hat Professor Reinhold Schnabel von der Universität Duisburg-Essen in einer Studie für die Initiative Neue Soziale Marktwirtschaft errechnet Grund dafür ist die in den kommenden Jahren drastisch ansteigende Zahl von alten Menschen. Die Zahl der Pflegebedürftigen wird danach bis zum Jahr 2020 auf 2,7 Millionen (heute: 2,1 Millionen) anwachsen. Im Jahr 2035 werden es bereits 3,5 Millionen Menschen sein, weil die geburtenstarken Jahrgänge dann das typische Pflegealter erreichen. Gleichzeitig schrumpft auf Grund der allgemeinen demografischen Entwicklung aber die Zahl der Beitragszahler in die gesetzliche Pflegeversicherung. Reinhold Schnabel: \"Die Reform der Pflegeversicherung ist dringend notwendig. Die Bürger brauchen Planungssicherheit, um genügend Zeit für die Gestaltung ihrer eigenen Vorsorge zu haben.\"",
  "b_id": "+pb+o1cL8kIN5PQzIfQJCQGTOgM=",
  "b_publication": "ntvde",
  "b_date": "2021-06-05T00:00:00",
  "b_author": "n-tv NACHRICHTEN",
  "b_url": "https://www.n-tv.de/panorama/Elektrobus-Depot-brennt-komplett-aus-article22599179.html",
  "b_text": "Elektrobus-Depot brennt komplett aus\nRauchsäule über Hannover Elektrobus-Depot brennt komplett aus In einem Depot der Verkehrsbetriebe in Hannover brennt ab, was die Busfauna so hergibt: fünf Elektrobusse, zwei Hybridbusse, ein Dieselbus und ein Reisebus. Besonders die E-Busse stellen die Feuerwehr bei den Löscharbeiten vor eine Herausforderung. Videos zeigen eine hohe Rauchsäule über der Stadt. Ein Brand in einem Bus-Depot in Hannover hat zu einem Millionenschaden und einem Großeinsatz der Feuerwehr geführt. Über Hannover war zeitweise eine hohe Rauchsäule zu sehen. Nach Angaben der Feuerwehr war in einer Fahrzeughalle der Verkehrsbetriebe Üstra, in der auch Elektro-Busse abgestellt waren, ein Feuer ausgebrochen. Die Feuerwehr rückte mit einem Großaufgebot und mehreren Drehleitern an. Es sei die vierte von fünf Alarmstufen ausgelöst worden, sagte Feuerwehrsprecher Hartmut Meyer. Bei dem Einsatz habe sich ein Feuerwehrmann verletzt. Er wurde ins Krankenhaus gebracht, konnte allerdings nach kurzer Zeit wieder entlassen werden. Das Feuer war am Nachmittag unter Kontrolle, die Löscharbeiten dauerten jedoch am Abend noch an. Üstra-Sprecher Udo Iwannek zufolge kam es durch den Brand zu einem Millionenschaden. Insgesamt seien neun Busse ausgebrannt, darunter fünf Elektrobusse, zwei Hybridbusse, ein Dieselbus und ein Reisebus. Auch die Ladeinfrastruktur habe Schaden genommen. Glücklicherweise habe eine Brandschutzwand den Flammen Stand gehalten, sagte Iwannek. Rund 25 weitere Busse, die in der Halle geparkt waren, hätten dadurch keinen Schaden genommen. Über Hannover war zeitweise eine hohe Rauchsäule zu sehen. Mehrere Videos in den sozialen Netzwerken zeigten dies. Unter einer Videofolge eines Users aus Hannover auf Twitter kommentieren die Verkehrsbetriebe: \"Das ist richtig. Auf dem Betriebshof in Mittelfeld gibt es aktuell einen Brand.\" Hohe Wärmestrahlung von den Batterien Besonders der Brand der E-Busse stellte die Feuerwehr vor eine Herausforderung bei den Löscharbeiten. Von den Batterien der Busse gehe eine hohe Wärmestrahlung aus, sagte Feuerwehrsprecher Meyer. Für die Rettungskräfte war es demnach schwierig, nah an den Brandort zu kommen. Auch die einsturzgefährdete Halle stellte ein Risiko dar. Unerwartete Hilfe kam für die Rettungskräfte allerdings vom Himmel in Form eines heftigen Platzregens. \"Das war für die Löscharbeiten hervorragend\", sagte Meyer. Wenn die Batterien von E-Autos in Brand geraten, kann es zu Knallen und einer gewaltigen Rußwolke kommen. Über dem Üstra-Gelände im Stadtteil Mittelfeld stand zeitweise eine dunkle Rauchwolke. Die Bevölkerung wurde aufgerufen, Fenster und Türen geschlossen zu halten. Informationen über Schadstoffe in der Luft gab es zunächst aber nicht. Aufgrund des Feuerwehreinsatzes konnten die Verkehrsbetriebe im Stadtteil Mittelfeld mehrere Haltestellen nicht anfahren, wie die Üstra auf Twitter mitteilte. Durch den Brand der Fahrzeuge seien aber keine Einschränkungen im Nahverkehr zu Wochenbeginn abzusehen, sagte Iwannek. Dann sollen Reserve-Busse eingesetzt werden. Quelle: ntv.de, mpe/dpa",
  "scores": "{\"1\": 0.16822429906542055, \"2\": 0.04271356783919598, \"3\": 0.008830022075055188, \"4\": 0.0, \"5\": 0.0, \"hapax\": 0.03676470588235294, \"1_mod\": 0.8686316611360531, \"2_mod\": 0, \"3_mod\": 1.0, \"4_mod\": 0.0, \"5_mod\": 0.0}"
}