{
  "a_id": "kpNELW/tFREvTmL6DezDLAmvMz4=",
  "a_publication": "insm_presse",
  "a_date": "2015-06-15T00:00:00",
  "a_author": null,
  "a_url": "https://www.insm.de/insm/presse/pressemeldungen/ttip-studie",
  "a_text": "Studie: TTIP wäre das richtige Signal\nDie Transatlantische Handels- und Investitionspartnerschaft (TTIP) könnte gegen ein wichtiges Liberalisierungssignal setzen, langfristig Arbeitsplätze sichern und zu mehr Wohlstand bei den Konsumenten und auf beiden Seiten des Atlantiks führen, so das Ergebnis eines Gutachten des Instituts der deutschen Wirtschaft Köln (IW). 15. Juni 2015 Pressemeldung TTIP-StudieINSM-Position zu TTIPPodcast zu InvestorenschutzWas TTIP bringt (Die Welt)Was TTIP bringt (Blog) Der freie Warenverkehr, dem der Exportweltmeister Deutschland seinen hohen Lebensstandard verdankt, ist in Gefahr. Protektionismus und Globalisierungsskepsis nehmen in der Welthandelspolitik zu. Die Transatlantische Handels- und Investitionspartnerschaft (TTIP) zwischen den USA und der EU könnte gegen diesen Trend ein wichtiges Liberalisierungssignal setzen, langfristig Arbeitsplätze sichern und zu mehr Wohlstand bei den Konsumenten und auf beiden Seiten des Atlantiks führen. Zu diesem Ergebnis kommt ein Gutachten des Instituts der deutschen Wirtschaft Köln (IW) im Auftrag der Initiative Neue Soziale Marktwirtschaft (INSM). Allein im Industriewarenhandel könnten nach IW-Schätzungen rund 3,5 Milliarden Euro Zollabgaben wegfallen, die bisher Güter unnötig verteuern. Besonders kleinen und mittleren Unternehmen würden durch die Partnerschaft neue Exportmöglichkeiten eröffnet. „Grenzüberschreitender Handel ist Teil des Deutschland-Prinzips und eine tragende Säule der Sozialen Marktwirtschaft. Ohne freien Zugang zum Weltmarkt hätte Deutschland weder den Wiederaufbau, noch die Wiedervereinigung meistern können. Wenn TTIP scheitert, geraten Arbeitsplätze in Gefahr, die Wirtschaftskraft sinkt und unsere ohnehin belasteten Sozialkassen geraten unter Druck“, kommentiert INSM-Geschäftsführer Hubertus Pellengahr die Ergebnisse der Studie. „Die meisten von den TTIP-Skeptikern hervorgebrachten Kritikpunkte erweisen sich bei genauer Betrachtung als überzogen und ideologisch motiviert. Die berechtigten Sorgen müssen hingegen adressiert und ernst genommen werden. Unlösbare Probleme sehe ich nicht“, so Studienautor Jürgen Matthes. So sollte beispielsweise die Verhandlungstransparenz so hoch sein, dass Parlamente und Öffentlichkeit ausreichend informiert sind und sie die Verhandlungen effizient und konstruktiv begleiten können. Genauso müsse überprüft werden, dass die Zusagen der Politik über die Beibehaltung der Verbraucher-, Umwelt- und Gesundheitsschutzstandards eingehalten werden und es zu keiner Absenkung der EU-Standards kommt. TTIP sollte als Chance zur Gestaltung begriffen werden. „Ein Scheitern der Verhandlungen würde ein fatales Signal über die Handlungsfähigkeit Deutschlands und Europas an die Welt senden. Wenn Europa nicht seine hohen Standards mit den USA gemeinsam festlegt, werden andere sich mit geringeren zufrieden geben“, so die Befürchtung Pellengahrs. Pressesprecher Tel.: 030-27877 174 Fax.: 030-27877 181 E-Mail: hennet@insm.de Twitter: @INSMPresse",
  "b_id": "Bq0EeSELbdzvL+KbETKN2xk7tXs=",
  "b_publication": "RND_de",
  "b_date": "2021-01-21T00:00:00",
  "b_author": "RND RedaktionsNetzwerk Deutschland",
  "b_url": "https://www.rnd.de/politik/fall-nawalny-russlands-aussenminister-lawrow-bezeichnet-deutsche-hilfe-als-unwurdig-ZTW4ZF7AITE6LHUEHGJRLJJQL4.html",
  "b_text": "Aufklärung im Fall Nawalny: Lawrow bezeichnet deutsche Hilfe als „unwürdig“\nStartseite Politik Fall Nawalny: Russlands Außenminister Lawrow bezeichnet deutsche Hilfe als „unwürdig“ Das Bundesamt für Justiz hat im Fall des Kremlkritikers Alexej Nawalny nach eigener Auskunft auf vier russische Rechtshilfeersuchen geantwortet. Die russische Generalstaatsanwaltschaft betrachtet diese Antworten allerdings als unzureichend. Sie wirft Deutschland vor, die „wahren Umstände des Vorfalls“ verschleiern zu wollen – und schickt eine neue Anfrage. Moskau. Im Fall des vergifteten Kremlkritikers Alexej Nawalny hat die russische Generalstaatsanwaltschaft eine neue Anfrage an die deutsche Justiz geschickt. Da die meisten Gesuche der russischen Ermittler abgelehnt worden seien und die Abschriften der Vernehmungen von Nawalny und seiner Frau nicht enthalten gewesen seien, würden vorherigen Rechtshilfegesuche als inhaltlich völlig unzureichend betrachtet, teilte die Behörde am Donnerstag in Moskau mit. Das Bundesamt für Justiz hatte zuvor erklärt, vier russische Rechtshilfegesuche zum Anschlag auf Nawalny beantwortet zu haben. Nach Ansicht der russischen Generalstaatsanwaltschaft deuten diese Aussagen darauf hin, dass die „wahren Umstände des Vorfalls“ verschleiert werden sollten. Der russische Außenminister Sergej Lawrow hatte die Antworten aus Deutschland als „unwürdig“ bezeichnet. Mit der neuen Anfrage wollen die russischen Behörden nach eigenen Angaben erreichen, dass die deutsche Seite den im vergangenen Jahr verschickten Rechtshilfegesuchen „in vollem Umfang“ nachkomme. Wie die russische Generalstaatsanwaltschaft mitteilte, sei von deutscher Seite verschiedenen russischen Rechtshilfeersuchen nicht entsprochen worden, so auch nicht der Bitte um eine Befragung der behandelnden Ärzte Nawalnys. Verweigert worden sei auch die Übermittlung der „medizinischen Dokumente, Krankheitsgeschichte, Kopien der gerichtsmedizinischen Gutachten, der toxikologischen und weiteren Laboruntersuchungen“. „Das Ersuchen um die Bereitstellung von Nawalnys Proben zwecks vergleichender Tests“ sei ebenfalls abgelehnt worden, heißt es in einer Mitteilung der Generalstaatsanwaltschaft. Den vorgelegten Unterlagen zufolge habe die deutsche Seite eine toxikologische Untersuchung von Flaschen durchgeführt, an denen Spuren des Nervenkampstoffes der Nowitschok-Gruppe nachgewiesen worden sein sollen. Im Nachgang zu den Untersuchungen lieferte die deutsche Seite jedoch keine konkreten Befunde und legte somit nahe, man soll ihr das Ganze aufs Wort glauben, kritisiert die russische Ermittlungsbehörde. Es seien auch keine Angaben zu Experten gemacht worden, die die Untersuchung durchgeführt haben. Deren Befragung sei ebenfalls abgelehnt worden. Der Oppositionspolitiker Nawalny war am 20. August in Russland Opfer eines Anschlags mit dem Nervengift Nowitschok geworden und wurde danach in Berlin behandelt. Er macht ein unter dem Befehl des russischen Präsidenten Wladimir Putin stehendes „Killerkommando“ des Inlandsgeheimdienstes FSB für das Attentat in der sibirischen Stadt Tomsk verantwortlich. Putin und der FSB weisen die Vorwürfe zurück. Nawalny war am Sonntag zurück nach Moskau geflogen und noch am Flughafen festgenommen worden. Nur einen Tag später hatte ihn ein Gericht zu 30 Tagen Haft verurteilt. Der Oppositionelle rief seine Anhänger für den kommenden Samstag landesweit zu Protesten auf. ZUM THEMA Die russischen Behörden forderten indes die sozialen Netzwerke Vkontake und Tik Tok auf, an Minderjährige gerichtete Aufrufe zu Protesten nicht weiter zu verbreiten. Viele junge Russen filmten sich zuletzt beim Anziehen und Packen für die neuen Kundgebungen. RND/dpa",
  "scores": "{\"1\": 0.16733067729083664, \"2\": 0.0455531453362256, \"3\": 0.005836575875486381, \"4\": 0.0, \"5\": 0.0, \"hapax\": 0.041916167664670656, \"1_mod\": 0.8686556927297668, \"2_mod\": 0.11153358681875793, \"3_mod\": 1.0, \"4_mod\": 0.0, \"5_mod\": 0.0}"
}