{
  "a_id": "sVFro5FUViG7KDYc+BywKiTtiqs=",
  "a_publication": "insm_presse",
  "a_date": "2020-03-26T00:00:00",
  "a_author": null,
  "a_url": "https://www.insm.de/insm/presse/pressemeldungen/die-rentenformel-muss-gerechter-werden",
  "a_text": "Die Rentenformel muss gerechter werden\nDie jüngeren Generationen tragen die Hauptlast des demografischen Wandels. Wenn künftig die Anzahl der Rentner steigt und die der Beitragszahler sinkt, müssen höhere Kosten von weniger Schultern getragen werden. Um die unverhältnismäßige Belastung der Beitragszahler zu reduzieren, schlägt die Initiative Neue Soziale Marktwirtschaft (INSM) daher vor, die Rentenformel gerechter zu machen. 26. März 2020 Pressemitteilung herunterladen (PDF)Gutachten herunterladen (PDF) In einer Studie für die INSM hat das Institut der deutschen Wirtschaft (IW) dargelegt, welche Auswirkungen eine Anpassung der Rentenformel auf Beiträge und Renten hätte. Im Zentrum steht dabei der sogenannte Nachhaltigkeitsfaktor. Seine Gewichtung sollte nach Meinung der INSM von derzeit 0,25 auf 0,33 angehoben werden. Das würde bewirken, dass die Rentner künftig ein Drittel der demografischen Belastung tragen, die Beitragszahler zwei Drittel. Derzeit tragen die Rentenbezieher nur ein Viertel, die Beitragszahler drei Viertel. Der Geschäftsführer der INSM, Hubertus Pellengahr, appelliert an Bundesregierung, sich für mehr Generationengerechtigkeit einzusetzen: „Derzeit tragen die jüngeren Generationen die Hauptlast des demografischen Wandels. Die faire Anpassung der Rentenformel entlastet die Beitragszahler und hält das Rentenniveau stabil.“ Bliebe die Gewichtung des Nachhaltigkeitsfaktors unverändert, würde der Beitragssatz bis 2060 auf 23,7 Prozent steigen und das Rentenniveau auf 43,7 Prozent sinken.* Durch die von der INSM geforderte Anpassung, stiege der Beitragssatz nur auf 22,6 Prozent, während das Rentenniveau moderat auf 43,1 Prozent sänke. Da ab 2030 die Rente mit 67 gilt, wird in beiden Fällen davon ausgegangen, dass ab 2031 zur Berechnung der Standardrente 47 Versicherungsjahre zugrunde gelegt werden. Diese Reform stellt aus Sicht der INSM eine wichtige Stellraube gerechter ein, kann aber grundlegende Reformen nicht ersetzen. Pellengahr: „Die Anpassung des Renteneintrittsalters an die Lebenserwartung ist eine politische Herkulesaufgabe. Die jetzige Bunderegierung sieht sich offenbar dieser Aufgabe nicht gewachsen. Das erhöht den Druck auf künftige Regierungen, frühzeitig und verlässlich die Weichen für ein längeres Arbeitsleben zu stellen.“ * Die Corona-Krise wird sich erheblich auf die gesetzliche Rentenversicherung auswirken. Noch ist es zu früh, hier genaue Vorhersagen auf Grundlage empirischer Daten zu machen. Eines ist aber schon jetzt klar: Der Reformbedarf wächst zusätzlich. Andernfalls bremsen unkontrolliert steigende Lohnnebenkosten künftiges Wachstum und verhindern eine rasche Erholung. Die heute vorgestellte Studie basiert auf Annahmen aus der Vorkrisenzeit. Die veränderten Rahmenbedingungen ändern nichts an den in der Studie dargestellten Zusammenhängen und Auswirkungen. Nur die konkreten Zahlen werden deutlich anders ausfallen. Eine entsprechende Aktualisierung erfolgt, sobald belastbare Daten zur Verfügung stehen. Pressesprecher Tel.: 030-27877 174 Fax.: 030-27877 181 E-Mail: hennet@insm.de Twitter: @INSMPresse",
  "b_id": "i5X0l1osieaWLRHLbCn29YI7ne0=",
  "b_publication": "FOCUS_TopNews",
  "b_date": "2021-05-14T00:00:00",
  "b_author": "FOCUS Online",
  "b_url": "https://www.focus.de/wissen/natur/meteorologie/ungemuetliches-wochenende-schauer-und-gewitter-aprilwetter-im-mai-erhoeht-risiko-von-typ-2-tornados_id_13296705.html",
  "b_text": "Schauer und Gewitter: Aprilwetter im Mai erhöht Risiko von Typ-2-Tornados - Video\nEs bleibt weiterhin regnerisch. In den kommenden Tagen können sich viele Gewitter ausbilden. Aber dazwischen kommt auch immer wieder die Sonne durch. Durch Tiefdruckgebiete, die über Nordeuropa hinwegziehen, werden in den kommenden Tagen kühle Luftmassen nach Deutschland verfrachtet. Besonders in der Höhe ist die Luft verbreitet kalt genug, dass angewärmte Luft aus Bodennähe hoch aufsteigen kann. Die Luft ist also labil geschichtet. Bei einer solchen Luftschichtung können leicht Gewitter auftreten. Besonders jetzt, da die Sonne schon viel Kraft hat, wird die bodennahe Luft so aufgewärmt, dass sie aufsteigt und sich Wolken bilden. Sonne, Fronten und Konvergenzlinien bringen Regen Aber nicht nur Sonneneinstrahlung, sondern auch andere Mechanismen, können Gewitter auslösen. Ein wichtiger Faktor ist die Hebung, wenn die Luft gezwungen wird, aufzusteigen. Darunter fallen zum Beispiel Kaltfronten, die die warme Luft vor der Front anheben. Die Hebung tritt auch bei Konvergenzlinien auf, an denen Wind aus unterschiedlichen Richtungen aufeinandertrifft. Und bis einschließlich Dienstag treten beide Phänomene in Deutschland auf. Schauer und Gewitter, aber ab und an auch Sonne Am Freitag und Samstag gibt es im Norden Deutschlands eine Konvergenzlinie, die Gewitter verursacht. Zusätzlich zum Gewitterrisiko erhöht eine Konvergenzlinie auch das Risiko für einen Tornado Typ 2. Dieser Tornado-Typ ist sehr kurzlebig und nicht so kräftig wie ein Tornado, der aus einer Superzelle hervorgeht. Das Risiko eines Typ-2- Tornados ist im Moment nicht sehr hoch, aber vorhanden. Die Gewitter an der Konvergenzlinie können aber auf jeden Fall Starkregen bringen. Die Sonneneinstrahlung kann in ganz Deutschland immer wieder Schauer und Gewitter auslösen. Im Rest des Landes werden sie vermutlich schwächer ausfallen als im Norden. Der Wind ist zudem eher schwach ist, sodass keine starken Böen im Zusammenhang mit den Gewittern auftreten. Der Freitag ist der Tag, an dem sich die Sonne am längsten zeigt. Ab Samstag kommt es häufiger zu Schauern, aber auch die Sonne kommt zwischen den Regengüssen zum Vorschein. Es herrscht sozusagen Aprilwetter im Mai. Auch der Wochenstart verläuft nass Sonntag bis Dienstag ziehen dann Fronten über Deutschland hinweg. Wie schon in den Tagen zuvor können sich Schauer und Gewitter ausbilden. Der Wind frischt dann auch etwas auf, sodass es zu stärkeren Böen kommen kann. Die Temperaturen bleiben weiterhin unter dem Mittel für Mai. Maximal werden an die 20 Grad erreicht. Als Terzic über größten Triumph spricht, überraschen ihn BVB-Stars mit Bierdusche Das Original zu diesem Beitrag \"Schauer und Gewitter: Aprilwetter im Mai erhöht Risiko von Typ-2-Tornados\" stammt von The Weather Channel.",
  "scores": "{\"1\": 0.22966507177033493, \"2\": 0.03291139240506329, \"3\": 0.0044742729306487695, \"4\": 0.0, \"5\": 0.0, \"hapax\": 0.12781954887218044, \"1_mod\": 1.0, \"2_mod\": 0.18543956043956045, \"3_mod\": 1.0, \"4_mod\": 0.0, \"5_mod\": 0.0}"
}